MANIFEST.in
README
__init__.py
__pkginfo__.py
entities.py
hooks.py
schema.py
setup.py
site_cubicweb.py
sobjects.py
testutils.py
./__init__.py
./__pkginfo__.py
./entities.py
./hooks.py
./schema.py
./site_cubicweb.py
./sobjects.py
./testutils.py
./test/__init__.py
./test/pytestconf.py
./test/test_forge.py
./test/unittest_forge.py
./test/unittest_notification.py
./test/unittest_security.py
./views/__init__.py
./views/boxes.py
./views/doap.py
./views/document.py
./views/figures.py
./views/forms.py
./views/others.py
./views/project.py
./views/startup.py
./views/ticket.py
./views/version.py
cubicweb_forge.egg-info/PKG-INFO
cubicweb_forge.egg-info/SOURCES.txt
cubicweb_forge.egg-info/dependency_links.txt
cubicweb_forge.egg-info/requires.txt
cubicweb_forge.egg-info/top_level.txt
data/cubes.forge.css
data/project-icon.png
i18n/en.po
i18n/es.po
i18n/fr.po
migration/0.12.0_Any.py
migration/0.13.0_Any.py
migration/1.1.0_Any.py
migration/1.10.1_Any.py
migration/1.12.0_Any.py
migration/1.13.0_Any.py
migration/1.2.0_Any.py
migration/1.3.0_Any.py
migration/1.3.2_Any.py
migration/1.4.1_Any.py
migration/1.5.0_Any.py
migration/1.5.2_Any.py
migration/1.6.0_Any.py
migration/1.6.1_Any.py
migration/1.7.0_Any.py
migration/1.9.0_Any.py
migration/1.9.1_Any.py
migration/postcreate.py
test/test_forge.py
views/__init__.py
views/boxes.py
views/doap.py
views/document.py
views/figures.py
views/forms.py
views/others.py
views/project.py
views/startup.py
views/ticket.py
views/version.py
wdoc/ChangeLog_en
wdoc/ChangeLog_fr
wdoc/about_en.rst
wdoc/about_fr.rst
wdoc/add_content_forge_fr.rst
wdoc/add_relation_fr.rst
wdoc/custom_view_last_update_en.rst
wdoc/custom_view_last_update_fr.rst
wdoc/custom_view_rss_en.rst
wdoc/custom_view_rss_fr.rst
wdoc/interface_fr.jpg
wdoc/interface_fr.rst
wdoc/relations_fr.jpg
wdoc/release_en.rst
wdoc/release_fr.rst
wdoc/search_sample_queries_en.rst
wdoc/search_sample_queries_fr.rst
wdoc/toc.xml