Metadata-Version: 1.1
Name: cubicweb-forge
Version: 1.13.0
Summary: software forge component for the CubicWeb framework
Home-page: http://www.cubicweb.org/project/cubicweb-forge
Author: LOGILAB S.A. (Paris, FRANCE)
Author-email: contact@logilab.fr
License: LGPL
Platform: UNKNOWN
Classifier: Environment :: Web Environment
Classifier: Framework :: CubicWeb
Classifier: Programming Language :: Python
Classifier: Programming Language :: JavaScript
Classifier: Topic :: Software Development :: Bug Tracking
